{"nodes":[{"id":"readme_openscireader","label":"OpenSciReader","file_type":"document","source_file":"README.md","source_location":null,"source_url":null,"captured_at":null,"author":null,"contributor":null},{"id":"readme_local_pdf_layout_translation_pipeline","label":"Local PDF Layout Translation Pipeline","file_type":"document","source_file":"README.md","source_location":null,"source_url":null,"captured_at":null,"author":null,"contributor":null},{"id":"readme_private_python_worker_contract","label":"Private Python Worker Contract","file_type":"document","source_file":"README.md","source_location":null,"source_url":null,"captured_at":null,"author":null,"contributor":null},{"id":"readme_react_page_by_page_preview_replacement","label":"React Page-by-Page Preview Replacement","file_type":"document","source_file":"README.md","source_location":null,"source_url":null,"captured_at":null,"author":null,"contributor":null},{"id":"readme_dual_column_reading_mode","label":"Dual-column Reading Mode","file_type":"document","source_file":"README.md","source_location":null,"source_url":null,"captured_at":null,"author":null,"contributor":null},{"id":"readme_chunk_based_translation_preview","label":"Chunk-based Translation Preview","file_type":"document","source_file":"README.md","source_location":null,"source_url":null,"captured_at":null,"author":null,"contributor":null},{"id":"readme_whole_book_export","label":"Whole-book Export","file_type":"document","source_file":"README.md","source_location":null,"source_url":null,"captured_at":null,"author":null,"contributor":null},{"id":"readme_real_time_job_management","label":"Real-time Job Management","file_type":"document","source_file":"README.md","source_location":null,"source_url":null,"captured_at":null,"author":null,"contributor":null},{"id":"readme_websocket_event_streaming","label":"WebSocket Event Streaming","file_type":"document","source_file":"README.md","source_location":null,"source_url":null,"captured_at":null,"author":null,"contributor":null},{"id":"readme_go_orchestration_pipeline","label":"Go Orchestration Pipeline","file_type":"document","source_file":"README.md","source_location":null,"source_url":null,"captured_at":null,"author":null,"contributor":null},{"id":"readme_windows_installer","label":"Windows Installer","file_type":"document","source_file":"README.md","source_location":null,"source_url":null,"captured_at":null,"author":null,"contributor":null},{"id":"readme_python_worker","label":"python_worker","file_type":"document","source_file":"README.md","source_location":null,"source_url":null,"captured_at":null,"author":null,"contributor":null},{"id":"readme_runtime_webview2_windows_amd64","label":"runtime/webview2/windows-amd64","file_type":"document","source_file":"README.md","source_location":null,"source_url":null,"captured_at":null,"author":null,"contributor":null},{"id":"readme_standalone_runtime_package","label":"Standalone Runtime Package","file_type":"document","source_file":"README.md","source_location":null,"source_url":null,"captured_at":null,"author":null,"contributor":null},{"id":"readme_installed_runtime_from_user_config_storage","label":"Installed Runtime from User Config Storage","file_type":"document","source_file":"README.md","source_location":null,"source_url":null,"captured_at":null,"author":null,"contributor":null},{"id":"readme_development_fallback_worker","label":"Development Fallback Worker","file_type":"document","source_file":"README.md","source_location":null,"source_url":null,"captured_at":null,"author":null,"contributor":null},{"id":"readme_development_fallback_runtime","label":"Development Fallback Runtime","file_type":"document","source_file":"README.md","source_location":null,"source_url":null,"captured_at":null,"author":null,"contributor":null},{"id":"readme_runtime_packaging_rationale","label":"Runtime Packaging Rationale","file_type":"document","source_file":"README.md","source_location":null,"source_url":null,"captured_at":null,"author":null,"contributor":null},{"id":"readme_github_actions_release","label":"GitHub Actions Release Packaging","file_type":"document","source_file":"README.md","source_location":null,"source_url":null,"captured_at":null,"author":null,"contributor":null},{"id":"readme_slim_installer_asset","label":"Slim Installer Asset","file_type":"document","source_file":"README.md","source_location":null,"source_url":null,"captured_at":null,"author":null,"contributor":null},{"id":"readme_standalone_runtime_asset","label":"Standalone Runtime Asset","file_type":"document","source_file":"README.md","source_location":null,"source_url":null,"captured_at":null,"author":null,"contributor":null},{"id":"readme_reader_workflow","label":"Reader Workflow","file_type":"document","source_file":"README.md","source_location":null,"source_url":null,"captured_at":null,"author":null,"contributor":null},{"id":"readme_backend_api_reference","label":"Backend API Reference","file_type":"document","source_file":"README.md","source_location":null,"source_url":null,"captured_at":null,"author":null,"contributor":null},{"id":"readme_internal_translator","label":"internal/translator","file_type":"document","source_file":"README.md","source_location":null,"source_url":null,"captured_at":null,"author":null,"contributor":null},{"id":"readme_pdf_translate_http_go","label":"pdf_translate_http.go","file_type":"document","source_file":"README.md","source_location":null,"source_url":null,"captured_at":null,"author":null,"contributor":null},{"id":"graph_report_graph_report","label":"Graph Report","file_type":"document","source_file":"graphify-out/GRAPH_REPORT.md","source_location":null,"source_url":null,"captured_at":null,"author":null,"contributor":null},{"id":"graph_report_community_hubs_navigation","label":"Community Hubs Navigation","file_type":"document","source_file":"graphify-out/GRAPH_REPORT.md","source_location":null,"source_url":null,"captured_at":null,"author":null,"contributor":null},{"id":"graph_report_god_nodes","label":"God Nodes","file_type":"document","source_file":"graphify-out/GRAPH_REPORT.md","source_location":null,"source_url":null,"captured_at":null,"author":null,"contributor":null},{"id":"graph_report_surprising_connections","label":"Surprising Connections","file_type":"document","source_file":"graphify-out/GRAPH_REPORT.md","source_location":null,"source_url":null,"captured_at":null,"author":null,"contributor":null},{"id":"graph_report_hyperedges","label":"Hyperedges","file_type":"document","source_file":"graphify-out/GRAPH_REPORT.md","source_location":null,"source_url":null,"captured_at":null,"author":null,"contributor":null},{"id":"graph_report_communities","label":"Communities","file_type":"document","source_file":"graphify-out/GRAPH_REPORT.md","source_location":null,"source_url":null,"captured_at":null,"author":null,"contributor":null},{"id":"graph_report_ambiguous_edges_review","label":"Ambiguous Edges Review","file_type":"document","source_file":"graphify-out/GRAPH_REPORT.md","source_location":null,"source_url":null,"captured_at":null,"author":null,"contributor":null},{"id":"graph_report_knowledge_gaps","label":"Knowledge Gaps","file_type":"document","source_file":"graphify-out/GRAPH_REPORT.md","source_location":null,"source_url":null,"captured_at":null,"author":null,"contributor":null},{"id":"graph_report_suggested_questions","label":"Suggested Questions","file_type":"document","source_file":"graphify-out/GRAPH_REPORT.md","source_location":null,"source_url":null,"captured_at":null,"author":null,"contributor":null},{"id":"graph_report_community_logo_asset","label":"Logo Asset Community","file_type":"document","source_file":"graphify-out/GRAPH_REPORT.md","source_location":null,"source_url":null,"captured_at":null,"author":null,"contributor":null},{"id":"graph_report_community_project_documentation","label":"Project Documentation Community","file_type":"document","source_file":"graphify-out/GRAPH_REPORT.md","source_location":null,"source_url":null,"captured_at":null,"author":null,"contributor":null},{"id":"graph_report_openscireader_report","label":"OpenSciReader Report","file_type":"document","source_file":"graphify-out/GRAPH_REPORT.md","source_location":null,"source_url":null,"captured_at":null,"author":null,"contributor":null},{"id":"graph_report_openscireader_logo","label":"OpenSciReader Logo","file_type":"document","source_file":"graphify-out/GRAPH_REPORT.md","source_location":null,"source_url":null,"captured_at":null,"author":null,"contributor":null},{"id":"logo_openscireader_logo","label":"OpenSciReader Logo","file_type":"image","source_file":"assets/logo.png","source_location":null,"source_url":null,"captured_at":null,"author":null,"contributor":null},{"id":"logo_open_book","label":"Open Book","file_type":"image","source_file":"assets/logo.png","source_location":null,"source_url":null,"captured_at":null,"author":null,"contributor":null},{"id":"logo_magnifying_glass","label":"Magnifying Glass","file_type":"image","source_file":"assets/logo.png","source_location":null,"source_url":null,"captured_at":null,"author":null,"contributor":null},{"id":"logo_pdf_document","label":"PDF Document","file_type":"image","source_file":"assets/logo.png","source_location":null,"source_url":null,"captured_at":null,"author":null,"contributor":null}],"edges":[{"source":"readme_openscireader","target":"readme_local_pdf_layout_translation_pipeline","relation":"references","confidence":"EXTRACTED","confidence_score":1.0,"source_file":"README.md","source_location":null,"weight":1.0},{"source":"readme_local_pdf_layout_translation_pipeline","target":"readme_go_orchestration_pipeline","relation":"references","confidence":"EXTRACTED","confidence_score":1.0,"source_file":"README.md","source_location":null,"weight":1.0},{"source":"readme_local_pdf_layout_translation_pipeline","target":"readme_private_python_worker_contract","relation":"references","confidence":"EXTRACTED","confidence_score":1.0,"source_file":"README.md","source_location":null,"weight":1.0},{"source":"readme_local_pdf_layout_translation_pipeline","target":"readme_react_page_by_page_preview_replacement","relation":"references","confidence":"EXTRACTED","confidence_score":1.0,"source_file":"README.md","source_location":null,"weight":1.0},{"source":"readme_openscireader","target":"readme_dual_column_reading_mode","relation":"references","confidence":"EXTRACTED","confidence_score":1.0,"source_file":"README.md","source_location":null,"weight":1.0},{"source":"readme_dual_column_reading_mode","target":"readme_chunk_based_translation_preview","relation":"references","confidence":"EXTRACTED","confidence_score":1.0,"source_file":"README.md","source_location":null,"weight":1.0},{"source":"readme_openscireader","target":"readme_whole_book_export","relation":"references","confidence":"EXTRACTED","confidence_score":1.0,"source_file":"README.md","source_location":null,"weight":1.0},{"source":"readme_real_time_job_management","target":"readme_websocket_event_streaming","relation":"references","confidence":"EXTRACTED","confidence_score":1.0,"source_file":"README.md","source_location":null,"weight":1.0},{"source":"readme_openscireader","target":"readme_real_time_job_management","relation":"references","confidence":"EXTRACTED","confidence_score":1.0,"source_file":"README.md","source_location":null,"weight":1.0},{"source":"readme_runtime_packaging_rationale","target":"readme_local_pdf_layout_translation_pipeline","relation":"rationale_for","confidence":"EXTRACTED","confidence_score":1.0,"source_file":"README.md","source_location":null,"weight":1.0},{"source":"readme_runtime_packaging_rationale","target":"readme_windows_installer","relation":"rationale_for","confidence":"EXTRACTED","confidence_score":1.0,"source_file":"README.md","source_location":null,"weight":1.0},{"source":"readme_windows_installer","target":"readme_python_worker","relation":"references","confidence":"EXTRACTED","confidence_score":1.0,"source_file":"README.md","source_location":null,"weight":1.0},{"source":"readme_windows_installer","target":"readme_runtime_webview2_windows_amd64","relation":"references","confidence":"EXTRACTED","confidence_score":1.0,"source_file":"README.md","source_location":null,"weight":1.0},{"source":"readme_standalone_runtime_package","target":"readme_windows_installer","relation":"conceptually_related_to","confidence":"EXTRACTED","confidence_score":1.0,"source_file":"README.md","source_location":null,"weight":1.0},{"source":"readme_standalone_runtime_package","target":"readme_installed_runtime_from_user_config_storage","relation":"references","confidence":"EXTRACTED","confidence_score":1.0,"source_file":"README.md","source_location":null,"weight":1.0},{"source":"readme_standalone_runtime_package","target":"readme_development_fallback_worker","relation":"references","confidence":"EXTRACTED","confidence_score":1.0,"source_file":"README.md","source_location":null,"weight":1.0},{"source":"readme_standalone_runtime_package","target":"readme_development_fallback_runtime","relation":"references","confidence":"EXTRACTED","confidence_score":1.0,"source_file":"README.md","source_location":null,"weight":1.0},{"source":"readme_github_actions_release","target":"readme_slim_installer_asset","relation":"references","confidence":"EXTRACTED","confidence_score":1.0,"source_file":"README.md","source_location":null,"weight":1.0},{"source":"readme_github_actions_release","target":"readme_standalone_runtime_asset","relation":"references","confidence":"EXTRACTED","confidence_score":1.0,"source_file":"README.md","source_location":null,"weight":1.0},{"source":"readme_reader_workflow","target":"readme_standalone_runtime_package","relation":"references","confidence":"EXTRACTED","confidence_score":1.0,"source_file":"README.md","source_location":null,"weight":1.0},{"source":"readme_reader_workflow","target":"readme_dual_column_reading_mode","relation":"conceptually_related_to","confidence":"INFERRED","confidence_score":0.82,"source_file":"README.md","source_location":null,"weight":1.0},{"source":"readme_backend_api_reference","target":"readme_internal_translator","relation":"references","confidence":"EXTRACTED","confidence_score":1.0,"source_file":"README.md","source_location":null,"weight":1.0},{"source":"readme_backend_api_reference","target":"readme_pdf_translate_http_go","relation":"references","confidence":"EXTRACTED","confidence_score":1.0,"source_file":"README.md","source_location":null,"weight":1.0},{"source":"graph_report_graph_report","target":"graph_report_community_hubs_navigation","relation":"references","confidence":"EXTRACTED","confidence_score":1.0,"source_file":"graphify-out/GRAPH_REPORT.md","source_location":null,"weight":1.0},{"source":"graph_report_graph_report","target":"graph_report_god_nodes","relation":"references","confidence":"EXTRACTED","confidence_score":1.0,"source_file":"graphify-out/GRAPH_REPORT.md","source_location":null,"weight":1.0},{"source":"graph_report_graph_report","target":"graph_report_surprising_connections","relation":"references","confidence":"EXTRACTED","confidence_score":1.0,"source_file":"graphify-out/GRAPH_REPORT.md","source_location":null,"weight":1.0},{"source":"graph_report_graph_report","target":"graph_report_hyperedges","relation":"references","confidence":"EXTRACTED","confidence_score":1.0,"source_file":"graphify-out/GRAPH_REPORT.md","source_location":null,"weight":1.0},{"source":"graph_report_graph_report","target":"graph_report_communities","relation":"references","confidence":"EXTRACTED","confidence_score":1.0,"source_file":"graphify-out/GRAPH_REPORT.md","source_location":null,"weight":1.0},{"source":"graph_report_graph_report","target":"graph_report_ambiguous_edges_review","relation":"references","confidence":"EXTRACTED","confidence_score":1.0,"source_file":"graphify-out/GRAPH_REPORT.md","source_location":null,"weight":1.0},{"source":"graph_report_graph_report","target":"graph_report_knowledge_gaps","relation":"references","confidence":"EXTRACTED","confidence_score":1.0,"source_file":"graphify-out/GRAPH_REPORT.md","source_location":null,"weight":1.0},{"source":"graph_report_graph_report","target":"graph_report_suggested_questions","relation":"references","confidence":"EXTRACTED","confidence_score":1.0,"source_file":"graphify-out/GRAPH_REPORT.md","source_location":null,"weight":1.0},{"source":"graph_report_community_hubs_navigation","target":"graph_report_community_project_documentation","relation":"references","confidence":"EXTRACTED","confidence_score":1.0,"source_file":"graphify-out/GRAPH_REPORT.md","source_location":null,"weight":1.0},{"source":"graph_report_community_hubs_navigation","target":"graph_report_community_logo_asset","relation":"references","confidence":"EXTRACTED","confidence_score":1.0,"source_file":"graphify-out/GRAPH_REPORT.md","source_location":null,"weight":1.0},{"source":"graph_report_communities","target":"graph_report_openscireader_report","relation":"references","confidence":"EXTRACTED","confidence_score":1.0,"source_file":"graphify-out/GRAPH_REPORT.md","source_location":null,"weight":1.0},{"source":"graph_report_surprising_connections","target":"readme_openscireader","relation":"references","confidence":"EXTRACTED","confidence_score":1.0,"source_file":"graphify-out/GRAPH_REPORT.md","source_location":null,"weight":1.0},{"source":"graph_report_surprising_connections","target":"graph_report_openscireader_logo","relation":"references","confidence":"EXTRACTED","confidence_score":1.0,"source_file":"graphify-out/GRAPH_REPORT.md","source_location":null,"weight":1.0},{"source":"graph_report_hyperedges","target":"readme_openscireader","relation":"references","confidence":"EXTRACTED","confidence_score":1.0,"source_file":"graphify-out/GRAPH_REPORT.md","source_location":null,"weight":1.0},{"source":"graph_report_hyperedges","target":"readme_local_pdf_layout_translation_pipeline","relation":"references","confidence":"EXTRACTED","confidence_score":1.0,"source_file":"graphify-out/GRAPH_REPORT.md","source_location":null,"weight":1.0},{"source":"graph_report_hyperedges","target":"readme_python_worker","relation":"references","confidence":"EXTRACTED","confidence_score":1.0,"source_file":"graphify-out/GRAPH_REPORT.md","source_location":null,"weight":1.0},{"source":"graph_report_hyperedges","target":"graph_report_openscireader_logo","relation":"references","confidence":"EXTRACTED","confidence_score":1.0,"source_file":"graphify-out/GRAPH_REPORT.md","source_location":null,"weight":1.0},{"source":"graph_report_ambiguous_edges_review","target":"graph_report_openscireader_logo","relation":"references","confidence":"EXTRACTED","confidence_score":1.0,"source_file":"graphify-out/GRAPH_REPORT.md","source_location":null,"weight":1.0},{"source":"graph_report_openscireader_report","target":"graph_report_graph_report","relation":"conceptually_related_to","confidence":"INFERRED","confidence_score":0.84,"source_file":"graphify-out/GRAPH_REPORT.md","source_location":null,"weight":1.0},{"source":"logo_openscireader_logo","target":"logo_open_book","relation":"conceptually_related_to","confidence":"AMBIGUOUS","confidence_score":0.25,"source_file":"assets/logo.png","source_location":null,"weight":1.0},{"source":"logo_openscireader_logo","target":"logo_magnifying_glass","relation":"conceptually_related_to","confidence":"AMBIGUOUS","confidence_score":0.25,"source_file":"assets/logo.png","source_location":null,"weight":1.0},{"source":"logo_openscireader_logo","target":"logo_pdf_document","relation":"conceptually_related_to","confidence":"AMBIGUOUS","confidence_score":0.2,"source_file":"assets/logo.png","source_location":null,"weight":1.0},{"source":"logo_openscireader_logo","target":"readme_openscireader","relation":"semantically_similar_to","confidence":"INFERRED","confidence_score":0.92,"source_file":"assets/logo.png","source_location":null,"weight":1.0},{"source":"graph_report_openscireader_logo","target":"logo_openscireader_logo","relation":"semantically_similar_to","confidence":"INFERRED","confidence_score":0.9,"source_file":"graphify-out/GRAPH_REPORT.md","source_location":null,"weight":1.0},{"source":"graph_report_openscireader_logo","target":"readme_openscireader","relation":"conceptually_related_to","confidence":"INFERRED","confidence_score":0.83,"source_file":"graphify-out/GRAPH_REPORT.md","source_location":null,"weight":1.0},{"source":"readme_chunk_based_translation_preview","target":"readme_react_page_by_page_preview_replacement","relation":"conceptually_related_to","confidence":"INFERRED","confidence_score":0.85,"source_file":"README.md","source_location":null,"weight":1.0},{"source":"readme_real_time_job_management","target":"readme_backend_api_reference","relation":"conceptually_related_to","confidence":"INFERRED","confidence_score":0.81,"source_file":"README.md","source_location":null,"weight":1.0}],"hyperedges":[{"id":"openscireader_translation_stack","label":"OpenSciReader Translation Stack","nodes":["readme_openscireader","readme_local_pdf_layout_translation_pipeline","readme_private_python_worker_contract"],"relation":"form","confidence":"EXTRACTED","confidence_score":1.0,"source_file":"README.md"},{"id":"bundled_translation_runtime_packaging","label":"Bundled Translation Runtime Packaging","nodes":["readme_windows_installer","readme_python_worker","readme_standalone_runtime_package"],"relation":"form","confidence":"EXTRACTED","confidence_score":1.0,"source_file":"README.md"},{"id":"openscireader_logo_composition","label":"OpenSciReader Logo Composition","nodes":["logo_openscireader_logo","logo_open_book","logo_magnifying_glass"],"relation":"form","confidence":"INFERRED","confidence_score":0.74,"source_file":"assets/logo.png"}],"input_tokens":0,"output_tokens":0}